odoo/addons/base_public_holiday/README.rst
odoo/addons/base_public_holiday/__init__.py
odoo/addons/base_public_holiday/__manifest__.py
odoo/addons/base_public_holiday/i18n/base_public_holiday.pot
odoo/addons/base_public_holiday/models/__init__.py
odoo/addons/base_public_holiday/models/base_public_holiday.py
odoo/addons/base_public_holiday/models/base_public_holiday_line.py
odoo/addons/base_public_holiday/security/ir.model.access.csv
odoo/addons/base_public_holiday/static/description/icon.png
odoo/addons/base_public_holiday/views/base_public_holidays_views.xml
odoo/addons/base_public_holiday/wizards/__init__.py
odoo/addons/base_public_holiday/wizards/import_ics.py
odoo/addons/base_public_holiday/wizards/import_ics.xml
odoo14_addon_base_public_holiday-14.0.1.2.0.dist-info/METADATA
odoo14_addon_base_public_holiday-14.0.1.2.0.dist-info/WHEEL
odoo14_addon_base_public_holiday-14.0.1.2.0.dist-info/top_level.txt
odoo14_addon_base_public_holiday-14.0.1.2.0.dist-info/RECORD
