Metadata-Version: 2.1
Name: odoo14-addon-base_public_holiday
Version: 14.0.1.2.0
Summary: Base Public Holiday
Home-page: https://simetri-sinergi.id
Author: PT. Simetri Sinergi Indonesia,OpenSynergy Indonesia
License: LGPL-3
Classifier: Programming Language :: Python
Classifier: Framework :: Odoo
Classifier: Framework :: Odoo :: 14.0
Classifier: License :: OSI Approved :: GNU Lesser General Public License v3 (LGPLv3)
Requires-Python: >=3.6
Requires-Dist: icalendar
Requires-Dist: odoo<14.1dev,>=14.0a
